Workbook
Name scenario: '1 Master'!$B$4
Name tam: '2 Customers'!$B$5
Name units: '2 Customers'!$B$6
Name customers_per_unit: '2 Customers'!$B$9
Name transactions_per_unit: '2 Customers'!$B$10
Name transactions_venture: '2 Customers'!$B$11
Name revenue_per_unit: '2 Customers'!$E$15
Name cogs_per_unit: '2 Customers'!$G$15
Name headcount_per_unit: '3 HR'!$D$20
Name hr_cost_per_unit: '3 HR'!$F$20
Name line_ho_role_limit_engine_and_data_team: '3 HR'!$D$24
Name line_ho_role_model_risk: '3 HR'!$D$25
Name line_ho_role_product: '3 HR'!$D$26
Name ho_staff_cost: '3 HR'!$D$27
Name capital_per_unit: '4 Depreciation'!$F$5
Name depreciation_per_unit: '4 Depreciation'!$G$5
Name capital_head_office: '4 Depreciation'!$F$8
Name depreciation_head_office: '4 Depreciation'!$G$8
Name line_running_expected_credit_loss_on_the_drawn_balance: '5 Running'!$C$5
Name line_running_computing_and_payments_in_the_account_line: '5 Running'!$C$6
Name line_running_write_off_administration_and_legal: '5 Running'!$C$7
Name line_running_cell_tooling_case_system_and_telephony: '5 Running'!$C$8
Name line_running_shared_trainer: '5 Running'!$C$9
Name running_per_unit: '5 Running'!$E$10
Name line_ho_running_technology_run_the_limit_engine: '5 Running'!$C$15
Name line_ho_running_fraud_monitoring_on_funded_events: '5 Running'!$C$16
Name line_ho_running_other_head_office_people_the_all_people_total_less_the_named_teams: '5 Running'!$C$17
Name line_ho_running_standby_securitisation_route_annual_upkeep: '5 Running'!$C$18
Name line_ho_running_reserve_against_the_assumed_head_office_count: '5 Running'!$C$19
Name running_head_office: '5 Running'!$E$20
Name startup_per_unit: '6 Start-up'!$B$7
Name startup_charge_per_unit: '6 Start-up'!$B$9
Name line_development_stage_0_back_test_on_the_bank_s_own_account_history: '6 Start-up'!$B$12
Name line_development_outcome_ledger_build: '6 Start-up'!$B$13
Name line_development_seasoning_schedule_build: '6 Start-up'!$B$14
Name line_development_credit_line_element_build_and_conformance_test: '6 Start-up'!$B$15
Name line_development_funding_term: '6 Start-up'!$B$16
Name line_development_migration_notices_to_the_accounts_moving_to_the_levelled_line: '6 Start-up'!$B$17
Name line_development_stage_readings_at_each_release_gate: '6 Start-up'!$B$18
Name line_development_standby_securitisation_route_documentation_and_set_up: '6 Start-up'!$B$19
Name line_development_carrying_cost_of_the_pool_overlays_during_release: '6 Start-up'!$B$20
Name development_head_office: '6 Start-up'!$B$21
Name development_charge_per_month: '6 Start-up'!$B$22
Name book_per_unit: '7 Returns'!$B$4
Name book_capital_per_unit: '7 Returns'!$B$5
Name returns_per_unit: '7 Returns'!$B$8
Name returns_head_office: '7 Returns'!$B$10
Name book_at_scale: '7 Returns'!$B$11
Name book_capital_at_scale: '7 Returns'!$B$12
Name tax_per_unit: '8 Tax'!$B$5
Name tax_head_office: '8 Tax'!$B$6
Name unit_own_cost: '9 Unit costs'!$B$12
Name ho_costs: '9 Unit costs'!$B$13
Name ho_total: '9 Unit costs'!$B$15
Name ho_allocated_per_unit: '9 Unit costs'!$B$16
Name whole_cost_per_unit: '9 Unit costs'!$B$17
Name cost_per_transaction: '9 Unit costs'!$B$18
Name margin_of_safety: '10 Pricing'!$B$6
Name interim_price: '10 Pricing'!$B$5
Name verdict: '10 Pricing'!$B$8

Sheet 1 Master
A1: Credit facility line — Case B — Master Control of variables and assumed values
A2: Blue cells are inputs. Change them here only; every other tab is formulas. Scenario 1 = base, 2 = low end of every band, 3 = high end.
A4: Scenario (1 base · 2 low · 3 high) | B4: 1
A6: Variable | B6: Active value | C6: Base | D6: Low | E6: High | F6: Unit | G6: Tier | H6: Source | I6: Adverse end | J6: Key
A7: Reachable population (whole venture) | B7: =CHOOSE('1 Master'!$B$4,C7,D7,E7) | C7: 950000 | D7: 850000 | E7: 1050000 | F7: business current accounts | G7: 4 | H7: ⚠ AOM v10 §0 — accounts on the levelled line after migration; a public-source estimate of the bank's SME account base | I7: low | J7: market.total_reachable_population
A8: Share of reachable population that is not viable | B8: =CHOOSE('1 Master'!$B$4,C8,D8,E8) | C8: 0.2 | D8: 0.15 | E8: 0.25 | F8: share | G8: 4 | H8: ⚠ assumed — accounts with no observed flow, so no limit can be computed (C1 record, the flow-coverage input) | I8: high | J8: market.non_viable_share
A9: Reachable population one operating unit serves | B9: =CHOOSE('1 Master'!$B$4,C9,D9,E9) | C9: 316667 | D9: 316667 | E9: 316667 | F9: accounts | G9: 4 | H9: ⚠ AOM v10 §3b — one cell per ⚠ 333,000 accounts; 950,000 ÷ 3 cells | I9: low | J9: market.unit_population
A10: Steady-state penetration of the unit's viable population | B10: =CHOOSE('1 Master'!$B$4,C10,D10,E10) | C10: 0.3 | D10: 0.3 | E10: 0.3 | F10: share | G10: 4 | H10: ⚠ AOM v10 §0 — drawn accounts as a share of accounts with a limit (228,000 of 760,000); the balance band below carries the uncertainty | I10: low | J10: market.penetration_steady_state
A11: Transactions per customer per month | B11: =CHOOSE('1 Master'!$B$4,C11,D11,E11) | C11: 20 | D11: 15 | E11: 25 | F11: £ thousands of average drawn balance per drawn account | G11: 4 | H11: ⚠ AOM v10 §0 — average drawn balance £15–25k per drawn account; book £3.4–5.7bn | I11: low | J11: market.transactions_per_customer_per_month
A12: Drawn balance, per £1,000 carried for one month — share of transactions | B12: =CHOOSE('1 Master'!$B$4,C12,D12,E12) | C12: 1 | D12: 1 | E12: 1 | J12: product.0.share
A13: Drawn balance, per £1,000 carried for one month — price | B13: =CHOOSE('1 Master'!$B$4,C13,D13,E13) | C13: 11.6667 | D13: 11.25 | E13: 11.875 | F13: GBP | G13: 3 | H13: C6 record — 14.0% simple on the daily drawn balance = £140 per £1,000 a year (band ⚠ 135–142.5), no fee; ÷ 12 | I13: low | J13: product.0.price
A14: Drawn balance, per £1,000 carried for one month — cost of goods per transaction | B14: =CHOOSE('1 Master'!$B$4,C14,D14,E14) | C14: 1.875 | D14: 1.25 | E14: 2.5 | F14: GBP | G14: 4 | H14: ⚠ C10 record — funding at the measured deposit cost 1.5–3.0% a year on the drawn balance (£15–30 per £1,000); ÷ 12 | I14: high | J14: product.0.cogs
A15: Available hours per person per month | B15: =CHOOSE('1 Master'!$B$4,C15,D15,E15) | C15: 125 | D15: 116.7 | E15: 133.3 | F15: hours | G15: 4 | H15: ⚠ AOM v10 §3b — 1,400–1,600 productive hours a year per handler; ÷ 12 | I15: low | J15: hr.available_hours
A16: Exception handler — monthly cost per person | B16: =CHOOSE('1 Master'!$B$4,C16,D16,E16) | C16: 4792 | D16: 4167 | E16: 5417 | F16: GBP | G16: 4 | H16: ⚠ AOM v10 §3b — handlers £50–65k a year all-in; ÷ 12 | I16: high | J16: role.Exception handler.monthly_cost
A17: Cell lead — monthly cost per person | B17: =CHOOSE('1 Master'!$B$4,C17,D17,E17) | C17: 6667 | D17: 5833 | E17: 7500 | F17: GBP | G17: 4 | H17: ⚠ AOM v10 §3b — leads £70–90k a year all-in; ÷ 12 | I17: high | J17: role.Cell lead.monthly_cost
A18: Head office — Limit engine and data team — monthly cost per person | B18: =CHOOSE('1 Master'!$B$4,C18,D18,E18) | C18: 11667 | D18: 10000 | E18: 13333 | F18: GBP | G18: 4 | H18: ⚠ AOM v10 §3c — 25 people, £3–4m a year; per person per month | I18: high | J18: ho_role.limit_engine_and_data_team.monthly_cost
A19: Head office — Model risk — monthly cost per person | B19: =CHOOSE('1 Master'!$B$4,C19,D19,E19) | C19: 14583 | D19: 12500 | E19: 16667 | F19: GBP | G19: 4 | H19: ⚠ AOM v10 §3c — 10 people, £1.5–2m a year; per person per month | I19: high | J19: ho_role.model_risk.monthly_cost
A20: Head office — Product — monthly cost per person | B20: =CHOOSE('1 Master'!$B$4,C20,D20,E20) | C20: 10417 | D20: 8333 | E20: 12500 | F20: GBP | G20: 4 | H20: ⚠ AOM v10 §3c — 13 people, £1.3–1.95m a year; per person per month | I20: high | J20: ho_role.product.monthly_cost
A21: Running cost, operating unit — Expected credit loss on the drawn balance | B21: =CHOOSE('1 Master'!$B$4,C21,D21,E21) | C21: 2.5 | D21: 1.6667 | E21: 3.3333 | F21: GBP | G21: 4 | H21: ⚠ C1 record — loss rate on the flow-underwritten pool 2–4% a year (£20–40 per £1,000); ÷ 12; unmeasured until Stage 0's back-test | I21: high | J21: running.expected_credit_loss_on_the_drawn_balance.amount
A22: Running cost, operating unit — Computing and payments in the account line | B22: =CHOOSE('1 Master'!$B$4,C22,D22,E22) | C22: 0.2975 | D22: 0.1683 | E22: 0.4267 | F22: GBP | G22: 4 | H22: ⚠ AOM v10 §6 — computing 2.02–5.12 per £1,000 a year; ÷ 12 | I22: high | J22: running.computing_and_payments_in_the_account_line.amount
A23: Running cost, operating unit — Write-off administration and legal | B23: =CHOOSE('1 Master'!$B$4,C23,D23,E23) | C23: 0.4167 | D23: 0.25 | E23: 0.5833 | F23: GBP | G23: 4 | H23: ⚠ AOM v10 §6 — write-off administration and legal £3–7 per £1,000 a year; ÷ 12 | I23: high | J23: running.write_off_administration_and_legal.amount
A24: Running cost, operating unit — Cell tooling — case system and telephony | B24: =CHOOSE('1 Master'!$B$4,C24,D24,E24) | C24: 23750 | D24: 19167 | E24: 28333 | F24: GBP | G24: 4 | H24: ⚠ AOM v10 §3b — tooling £0.23–0.34m a year per cell; ÷ 12 | I24: high | J24: running.cell_tooling_case_system_and_telephony.amount
... A42: Cost of capital (annual) | B42: =CHOOSE('1 Master'!$B$4,C42,D42,E42) | C42: 0.135 | D42: 0.12 | E42: 0.15 | F42: share | G42: 3 | H42: ⚠ FIT model at C10 — cost of equity 12–15% on the capital held against the book (a bank's target return on tangible equity, public results) | I42: high | J42: finance.cost_of_capital
A43: Tax rate on investment returns | B43: =CHOOSE('1 Master'!$B$4,C43,D43,E43) | C43: 0.25 | D43: 0.25 | E43: 0.25 | F43: share | J43: finance.tax_rate
A44: Head-office target profit (share of head-office cost) | B44: =CHOOSE('1 Master'!$B$4,C44,D44,E44) | C44: 0 | D44: 0 | E44: 0 | F44: share | J44: finance.ho_target_ebit
A45: Target margin of safety | B45: =CHOOSE('1 Master'!$B$4,C45,D45,E45) | C45: 0.25 | D45: 0.25 | E45: 0.25 | F45: share | J45: finance.target_margin
A46: Balance lent per transaction (the book one transaction carries) | B46: =CHOOSE('1 Master'!$B$4,C46,D46,E46) | C46: 1000 | D46: 1000 | E46: 1000 | F46: GBP | G46: 1 | H46: by definition — one transaction is £1,000 of drawn balance carried for one month | J46: book.balance_per_transaction
A47: Share of the book the venture funds with its own capital | B47: =CHOOSE('1 Master'!$B$4,C47,D47,E47) | C47: 0.1148 | D47: 0.1071 | E47: 0.1224 | F47: share | G47: 2 | H47: 75% risk weight (CRR Art. 123, FACT) × ⚠ 12% total capital × (1 + 10% conversion on undrawn (Basel 3.1, PRA PS9/24, FACT) × ⚠ 1.9–3.6 undrawn per drawn); the rest of the book is funded by the pool's own credit balances (C10) | I47: high | J47: book.capital_share_of_balance
A48: Operating units open in year one | B48: =CHOOSE('1 Master'!$B$4,C48,D48,E48) | C48: 0.76 | D48: 0.76 | E48: 0.76 | J48: cashflow.year1_units
A49: Share of the at-scale head office staffed and run in year one | B49: =CHOOSE('1 Master'!$B$4,C49,D49,E49) | C49: 1 | D49: 1 | E49: 1 | F49: share | J49: cashflow.year1_head_office_share
A50: Opening cash balance | B50: =CHOOSE('1 Master'!$B$4,C50,D50,E50) | C50: 0 | D50: 0 | E50: 0 | J50: cashflow.opening_balance
A51: Loan amount | B51: =CHOOSE('1 Master'!$B$4,C51,D51,E51) | C51: 0 | D51: 0 | E51: 0 | J51: cashflow.loan_amount
A52: Loan interest rate (annual) | B52: =CHOOSE('1 Master'!$B$4,C52,D52,E52) | C52: 0 | D52: 0 | E52: 0 | F52: share | J52: cashflow.loan_rate_annual
A53: Loan term (months) | B53: =CHOOSE('1 Master'!$B$4,C53,D53,E53) | C53: 12 | D53: 12 | E53: 12 | J53: cashflow.loan_term_months
A54: Other equity or grants in month one | B54: =CHOOSE('1 Master'!$B$4,C54,D54,E54) | C54: 5000000 | D54: 5000000 | E54: 5000000 | J54: cashflow.other_equity
A55: Stress test: reduction in revenue | B55: =CHOOSE('1 Master'!$B$4,C55,D55,E55) | C55: 0.1 | D55: 0.1 | E55: 0.1 | F55: share | J55: cashflow.stress_revenue_reduction

Sheet 2 Customers
A1: Customer base and monthly transactions — one operating unit, then the venture
A2: Operating unit: exception cell — One handling cell — 11 to 15 handlers, a lead and shared tooling — serving one third of the reachable accounts; the automated limit, funding and collection run in the account line and cost per £1,000 drawn.
A4: Reachable population (whole venture) | B4: ='1 Master'!$B$7 | C4: Master
A5: Total addressable market = reachable × (1 − non-viable share) | B5: =B4*(1-'1 Master'!$B$8) | C5: IFC step 1
A6: Number of operating units = reachable ÷ population per unit, rounded up | B6: =ROUNDUP(B4/'1 Master'!$B$9,0) | C6: IFC step 1
A7: Reachable population per unit | B7: ='1 Master'!$B$9 | C7: Master
A8: Viable population per unit = reachable per unit × (1 − non-viable share) | B8: =B7*(1-'1 Master'!$B$8)
A9: Customer base per unit = viable population × penetration | B9: =B8*'1 Master'!$B$10 | C9: IFC step 1
A10: Transactions per unit per month = customers × frequency | B10: =B9*'1 Master'!$B$11 | C10: IFC step 1
A11: Transactions across the venture per month = units × per unit | B11: =B6*B10
A13: Product | B13: Share of transactions | C13: Transactions per unit per month | D13: Price | E13: Revenue per unit per month | F13: Cost of goods per transaction | G13: Cost of goods per unit per month
A14: Drawn balance, per £1,000 carried for one month | B14: ='1 Master'!$B$12 | C14: ='2 Customers'!$B$10*B14 | D14: ='1 Master'!$B$13 | E14: =C14*D14 | F14: ='1 Master'!$B$14 | G14: =C14*F14
A15: Total | B15: =SUM(B14:B14) | C15: =SUM(C14:C14) | E15: =SUM(E14:E14) | G15: =SUM(G14:G14)

Sheet 3 HR
A1: Human resource costs — activities, time, drivers, headcount
A2: Hours = minutes ÷ 60 × driver quantity × multiplier. Headcount = hours ÷ available hours, rounded up to whole people. IFC step 2.
A4: Activity | B4: Role | C4: Minutes | D4: Driver | E4: Multiplier | F4: Driver quantity per month | G4: Hours per month | H4: Note
A5: Flow stop — the account's receipts stop and the limit is held | B5: Exception handler | C5: 240 | D5: per_customer_month | E5: 0.0016667 | F5: ='2 Customers'!$B$9 | G5: =C5/60*F5*E5 | H5: ⚠ 2,000 events per 100,000 drawn accounts a year × 4 hours (AOM v10 §3b)
A6: Signal review — a conduct or fraud signal on a drawn account | B6: Exception handler | C6: 120 | D6: per_customer_month | E6: 0.0025 | F6: ='2 Customers'!$B$9 | G6: =C6/60*F6*E6 | H6: ⚠ 3,000 events × 2 hours
A7: Dispute — the customer contests a funded event or a charge | B7: Exception handler | C7: 60 | D7: per_customer_month | E7: 0.00083333 | F7: ='2 Customers'!$B$9 | G7: =C7/60*F7*E7 | H7: ⚠ 1,000 events × 1 hour
A8: Write-off case — the account is closed and the balance written off | B8: Exception handler | C8: 60 | D8: per_customer_month | E8: 0.00083333 | F8: ='2 Customers'!$B$9 | G8: =C8/60*F8*E8 | H8: ⚠ 1,000 events × 1 hour; the administration and legal cost is a running line below
A9: Saving statement query | B9: Exception handler | C9: 30 | D9: per_customer_month | E9: 0.0016667 | F9: ='2 Customers'!$B$9 | G9: =C9/60*F9*E9 | H9: ⚠ 2,000 events × 0.5 hours (C2)
A10: Limit history query | B10: Exception handler | C10: 15 | D10: per_customer_month | E10: 0.0055542 | F10: ='2 Customers'!$B$9 | G10: =C10/60*F10*E10 | H10: ⚠ 3,330–10,000 events × 0.25 hours (C4); the central count 6,665
A11: Funding query — why a payment was or was not funded | B11: Exception handler | C11: 15 | D11: per_customer_month | E11: 0.00090417 | F11: ='2 Customers'!$B$9 | G11: =C11/60*F11*E11 | H11: ⚠ 270–1,900 events × 0.25 hours (C5); the central count 1,085
A12: Charge query | B12: Exception handler | C12: 15 | D12: per_customer_month | E12: 0.00029167 | F12: ='2 Customers'!$B$9 | G12: =C12/60*F12*E12 | H12: ⚠ 200–500 events × 0.25 hours (C6); the central count 350
A13: Display query — the credit line as shown by a third-party provider | B13: Exception handler | C13: 15 | D13: per_customer_month | E13: 0.00035417 | F13: ='2 Customers'!$B$9 | G13: =C13/60*F13*E13 | H13: ⚠ 150–700 events × 0.25 hours (C7); the central count 425
A14: Seasoning query — why the limit rose or did not | B14: Exception handler | C14: 15 | D14: per_customer_month | E14: 0.00083333 | F14: ='2 Customers'!$B$9 | G14: =C14/60*F14*E14 | H14: ⚠ 500–1,500 events × 0.25 hours (C8); the central count 1,000
A15: Supervise the cell — one lead per cell | B15: Cell lead | C15: 7500 | D15: per_unit_month | E15: 1 | F15: =1 | G15: =C15/60*F15*E15 | H15: one full-time lead (125 hours a month) per cell, AOM v10 §3b
A17: Role | B17: Hours per month | C17: Available hours per person | D17: Headcount (rounded up) | E17: Monthly cost per person | F17: Role cost per month | G17: Utilisation
A18: Exception handler | B18: =SUMIF($B$5:$B$15,A18,$G$5:$G$15) | C18: ='1 Master'!$B$15 | D18: =ROUNDUP(B18/C18,0) | E18: ='1 Master'!$B$16 | F18: =D18*E18 | G18: =IF(D18=0,0,B18/(C18*D18))
A19: Cell lead | B19: =SUMIF($B$5:$B$15,A19,$G$5:$G$15) | C19: ='1 Master'!$B$15 | D19: =ROUNDUP(B19/C19,0) | E19: ='1 Master'!$B$17 | F19: =D19*E19 | G19: =IF(D19=0,0,B19/(C19*D19))
A20: Unit total | D20: =SUM(D18:D19) | F20: =SUM(F18:F19)
A22: Head office
A23: Role | B23: Count | C23: Monthly cost per person | D23: Cost per month
A24: Limit engine and data team | B24: 25 | C24: ='1 Master'!$B$18 | D24: =B24*C24
A25: Model risk | B25: 10 | C25: ='1 Master'!$B$19 | D25: =B25*C25
A26: Product | B26: 13 | C26: ='1 Master'!$B$20 | D26: =B26*C26
A27: Head office staff total | D27: =SUM(D24:D26)

Sheet 4 Depreciation
A1: Capital assets — cost, life, quantity, monthly depreciation
A2: Depreciation per month = cost × quantity ÷ life in months. IFC step 2.
A4: Asset (operating unit) | B4: Cost | C4: Life (months) | D4: Quantity driver | E4: Quantity | F4: Capital cost | G4: Depreciation per month
A5: Unit total | F5: =0 | G5: =0
A7: Asset (head office) | B7: Cost | C7: Life (months) | E7: Quantity | F7: Capital cost | G7: Depreciation per month
A8: Head office total | F8: =0 | G8: =0

Sheet 5 Running
A1: General running costs — driver-linked
A2: Cost per month = amount × driver quantity. IFC step 2.
A4: Item (operating unit) | B4: Driver | C4: Amount | D4: Driver quantity | E4: Cost per month
A5: Expected credit loss on the drawn balance | B5: per_transaction | C5: ='1 Master'!$B$21 | D5: ='2 Customers'!$B$10 | E5: =C5*D5
A6: Computing and payments in the account line | B6: per_transaction | C6: ='1 Master'!$B$22 | D6: ='2 Customers'!$B$10 | E6: =C6*D6
A7: Write-off administration and legal | B7: per_transaction | C7: ='1 Master'!$B$23 | D7: ='2 Customers'!$B$10 | E7: =C7*D7
A8: Cell tooling — case system and telephony | B8: per_unit_month | C8: ='1 Master'!$B$24 | D8: =1 | E8: =C8*D8
A9: Shared trainer | B9: per_unit_month | C9: ='1 Master'!$B$25 | D9: =1 | E9: =C9*D9
A10: Unit total | E10: =SUM(E5:E9)
A11: of which fixed per month (per unit and per head drivers) | E11: =SUMIF(B5:B9,"per_unit_month",E5:E9)+SUMIF(B5:B9,"per_head",E5:E9)
A12: of which varies with volume | E12: =E10-E11
A14: Item (head office) | C14: Amount per month | E14: Cost per month
A15: Technology run — the limit engine | C15: ='1 Master'!$B$26 | E15: =C15
A16: Fraud monitoring on funded events | C16: ='1 Master'!$B$27 | E16: =C16
A17: Other head-office people (the all-people total less the named teams) | C17: ='1 Master'!$B$28 | E17: =C17
A18: Standby securitisation route — annual upkeep | C18: ='1 Master'!$B$29 | E18: =C18
A19: Reserve against the assumed head-office count | C19: ='1 Master'!$B$30 | E19: =C19
A20: Head office total | E20: =SUM(E15:E19)

Sheet 6 Start-up
A1: Start-up working capital and development costs
A2: One-time costs plus working capital, spread over the investment recovery period. IFC step 3.
A4: Item (operating unit, one-time) | B4: Cost | C4: Note
A5: One-time start-up costs per unit | B5: =0
A6: Working capital = months × (cost of goods + staff + running) per month | B6: ='1 Master'!$B$40*('2 Customers'!$G$15+'3 HR'!$F$20+'5 Running'!$E$10) | C6: cash the unit needs before revenue covers running cost
A7: Start-up total per unit | B7: =B5+B6
A8: Investment recovery period (months) | B8: ='1 Master'!$B$41
A9: Start-up charge per unit per month = total ÷ period | B9: =B7/B8 | C9: IFC step 3
A11: Item (head office development, one-time) | B11: Cost | C11: Note
A12: Stage 0 back-test on the bank's own account history | B12: ='1 Master'!$B$31
A13: Outcome ledger build | B13: ='1 Master'!$B$32
A14: Seasoning schedule build | B14: ='1 Master'!$B$33
A15: Credit-line element build and conformance test | B15: ='1 Master'!$B$34
A16: Funding term | B16: ='1 Master'!$B$35
A17: Migration notices to the accounts moving to the levelled line | B17: ='1 Master'!$B$36
A18: Stage readings at each release gate | B18: ='1 Master'!$B$37
A19: Standby securitisation route — documentation and set-up | B19: ='1 Master'!$B$38
A20: Carrying cost of the pool overlays during release | B20: ='1 Master'!$B$39
A21: Development total | B21: =SUM(B12:B20)
A22: Development charge per month = total ÷ period | B22: =B21/'1 Master'!$B$41

Sheet 7 Returns
A1: Investment returns
A2: Return per month = (start-up + capital assets + capital held against the book) × cost of capital ÷ 12. IFC step 3.
A4: Loan book one unit carries = transactions × balance lent per transaction | B4: ='2 Customers'!$B$10*'1 Master'!$B$46
A5: Capital held against the book = book × capital share (the rest is deposit-funded) | B5: =B4*'1 Master'!$B$47
A6: Operating unit: capital invested = start-up + capital assets + capital held against the book | B6: ='6 Start-up'!$B$7+'4 Depreciation'!$F$5+B5
A7: Cost of capital (annual) | B7: ='1 Master'!$B$42
A8: Return required per unit per month | B8: =B6*B7/12
A9: Head office: capital invested = development + capital assets | B9: ='6 Start-up'!$B$21+'4 Depreciation'!$F$8
A10: Return required at head office per month | B10: =B9*B7/12
A11: Loan book at scale = units × book per unit | B11: ='2 Customers'!$B$6*B4
A12: Capital held against the book at scale = units × capital per unit | B12: ='2 Customers'!$B$6*B5

Sheet 8 Tax
A1: Tax on investment returns
A2: Tax per month = return per month × tax rate. IFC step 3.
A4: Tax rate | B4: ='1 Master'!$B$43
A5: Tax per unit per month | B5: ='7 Returns'!$B$8*B4
A6: Tax at head office per month | B6: ='7 Returns'!$B$10*B4

Sheet 9 Unit costs
A1: Operating unit — whole cost structure per month
A2: Every cost the unit carries, including its share of head office. IFC step 4 input.
A4: Line | B4: Per month | C4: Share | D4: From
A5: Cost of goods | B5: ='2 Customers'!$G$15 | C5: =B5/$B$17 | D5: 2 Customers
A6: Staff | B6: ='3 HR'!$F$20 | C6: =B6/$B$17 | D6: 3 HR
A7: Depreciation | B7: ='4 Depreciation'!$G$5 | C7: =B7/$B$17 | D7: 4 Depreciation
A8: General running | B8: ='5 Running'!$E$10 | C8: =B8/$B$17 | D8: 5 Running
A9: Start-up charge | B9: ='6 Start-up'!$B$9 | C9: =B9/$B$17 | D9: 6 Start-up
A10: Investment return | B10: ='7 Returns'!$B$8 | C10: =B10/$B$17 | D10: 7 Returns
A11: Tax | B11: ='8 Tax'!$B$5 | C11: =B11/$B$17 | D11: 8 Tax
A12: Unit's own costs | B12: =SUM(B5:B11)
A13: Head office costs per month | B13: ='3 HR'!$D$27+'5 Running'!$E$20+'4 Depreciation'!$G$8+'6 Start-up'!$B$22+'7 Returns'!$B$10+'8 Tax'!$B$6
A14: Head office target profit = head office costs × target margin | B14: =B13*'1 Master'!$B$44
A15: Head office total per month | B15: =B13+B14
A16: Head office allocated per unit = total ÷ number of units | B16: =B15/'2 Customers'!$B$6 | C16: =B16/$B$17
A17: Whole cost per unit per month | B17: =B12+B16
A18: Whole cost per transaction = whole cost ÷ transactions | B18: =B17/'2 Customers'!$B$10

Sheet 10 Pricing
A1: Pricing — cost floor, interim price, margin of safety, required price
A2: Margin of safety = (price − cost) ÷ cost. Gate: 25% or more passes; 15% to 24% borderline; under 15% fails. Required price = cost × (1 + target margin). IFC steps 4 and 5.
A4: Whole cost per transaction (cost floor) | B4: ='9 Unit costs'!$B$18
A5: Interim price per transaction (revenue ÷ transactions, at the prices on tab 1) | B5: ='2 Customers'!$E$15/'2 Customers'!$B$10
A6: Margin of safety = (price − cost) ÷ cost | B6: =(B5-B4)/B4
A7: Target margin of safety | B7: ='1 Master'!$B$45
A8: Verdict | B8: =IF(B6>=0.25,"PASS",IF(B6>=0.15,"BORDERLINE","FAIL"))
A9: Required price per transaction = cost × (1 + target) | B9: =B4*(1+B7)
A10: Price uplift needed to reach target (required ÷ interim) | B10: =B9/B5
A11: Margin from failure: margin of safety less the 15% floor (percentage points) | B11: =B6-0.15
A12: Price fall that takes the margin of safety to the 15% floor | B12: =B5-B4*(1+0.15)
A14: Product | B14: Interim price | C14: Required price at target | D14: Share of transactions
A15: Drawn balance, per £1,000 carried for one month | B15: ='1 Master'!$B$13 | C15: =B15*'10 Pricing'!$B$10 | D15: ='1 Master'!$B$12
A18: Sensitivity — one input at a time moved to its adverse end (values computed by the generator from the same inputs; not live — change the scenario on tab 1 to see every band at once)
A19: Input | B19: Adverse end | C19: Value used | D19: Margin of safety | E19: Change from base
A20: Running cost, operating unit — Expected credit loss on the drawn balance | B20: high | C20: 3.3333 | D20: 0.47994681 | E20: -0.17493038
A21: Drawn balance, per £1,000 carried for one month — cost of goods per transaction | B21: high | C21: 2.5 | D21: 0.52011325 | E21: -0.13476394
A22: Drawn balance, per £1,000 carried for one month — price | B22: low | C22: 11.25 | D22: 0.59576987 | E22: -0.059107316
A23: Cost of capital (annual) | B23: high | C23: 0.15 | D23: 0.61314605 | E23: -0.041731139
A24: Running cost, operating unit — Write-off administration and legal | B24: high | C24: 0.5833 | D24: 0.61667266 | E24: -0.038204527
A25: Start-up working capital (months of unit running cost) | B25: high | C25: 1 | D25: 0.61859873 | E25: -0.036278464
A26: Running cost, operating unit — Computing and payments in the account line | B26: high | C26: 0.4267 | D26: 0.62509484 | E26: -0.02978235
A27: Transactions per customer per month | B27: low | C27: 15 | D27: 0.62821608 | E27: -0.026661108
A28: Share of the book the venture funds with its own capital | B28: high | C28: 0.1224 | D28: 0.6301642 | E28: -0.024712986
A29: Development cost, head office, one-time — Carrying cost of the pool overlays during release | B29: high | C29: 10400000 | D29: 0.64669218 | E29: -0.0081850058
A30: Running cost, head office, per month — Reserve against the assumed head-office count | B30: high | C30: 300333 | D30: 0.64717443 | E30: -0.0077027598
A31: Share of reachable population that is not viable | B31: high | C31: 0.25 | D31: 0.64947535 | E31: -0.0054018433
... A53: Reachable population (whole venture) | B53: low | C53: 850000 | D53: 0.65487719 | E53: 0
A54: Binding input (largest fall in the margin of safety) | B54: Running cost, operating unit — Expected credit loss on the drawn balance
A55: Margin of safety with every input at its adverse end (worst corner) | B55: 0.14514055
A56: Margin of safety at base, as computed by the builder (must equal B6) | B56: 0.65487719

Sheet 11 Unit P&L
A1: Synthesis — whole-cost profit and loss, one operating unit per month
A2: At the interim price and at the required price. Surplus ÷ whole cost recomputes the margin of safety. IFC step 5.
A4: Line | B4: At interim price | C4: At required price | D4: Note
A5: Transactions per month | B5: ='2 Customers'!$B$10 | C5: ='2 Customers'!$B$10
A6: Price per transaction | B6: ='2 Customers'!$E$15/'2 Customers'!$B$10 | C6: ='10 Pricing'!$B$9
A7: Revenue | B7: =B5*B6 | C7: =C5*C6
A8: Cost of goods | B8: =-'2 Customers'!$G$15 | C8: =-'2 Customers'!$G$15
A9: Staff | B9: =-'3 HR'!$F$20 | C9: =-'3 HR'!$F$20
A10: Depreciation | B10: =-'4 Depreciation'!$G$5 | C10: =-'4 Depreciation'!$G$5
A11: General running | B11: =-'5 Running'!$E$10 | C11: =-'5 Running'!$E$10
A12: Start-up charge | B12: =-'6 Start-up'!$B$9 | C12: =-'6 Start-up'!$B$9
A13: Investment return | B13: =-'7 Returns'!$B$8 | C13: =-'7 Returns'!$B$8
A14: Tax | B14: =-'8 Tax'!$B$5 | C14: =-'8 Tax'!$B$5
A15: Head office allocation | B15: =-'9 Unit costs'!$B$16 | C15: =-'9 Unit costs'!$B$16
A16: Whole cost | B16: =SUM(B8:B15) | C16: =SUM(C8:C15)
A17: Surplus = revenue + whole cost | B17: =B7+B16 | C17: =C7+C16
A18: Surplus ÷ whole cost (recomputed margin of safety) | B18: =B17/-B16 | C18: =C17/-C16

Sheet 12 Venture P&L
A1: Synthesis — whole-cost profit and loss, the venture at scale, per month
A2: Every operating unit plus head office. Venture surplus must equal units × unit surplus. IFC step 5.
A4: Line | B4: Per unit | C4: Units | D4: Venture per month
A5: Revenue | B5: ='2 Customers'!$E$15 | C5: ='2 Customers'!$B$6 | D5: =B5*C5
A6: Cost of goods | B6: =-'2 Customers'!$G$15 | C6: ='2 Customers'!$B$6 | D6: =B6*C6
A7: Staff (units) | B7: =-'3 HR'!$F$20 | C7: ='2 Customers'!$B$6 | D7: =B7*C7
A8: Depreciation (units) | B8: =-'4 Depreciation'!$G$5 | C8: ='2 Customers'!$B$6 | D8: =B8*C8
A9: General running (units) | B9: =-'5 Running'!$E$10 | C9: ='2 Customers'!$B$6 | D9: =B9*C9
A10: Start-up charge (units) | B10: =-'6 Start-up'!$B$9 | C10: ='2 Customers'!$B$6 | D10: =B10*C10
A11: Investment return (units) | B11: =-'7 Returns'!$B$8 | C11: ='2 Customers'!$B$6 | D11: =B11*C11
A12: Tax (units) | B12: =-'8 Tax'!$B$5 | C12: ='2 Customers'!$B$6 | D12: =B12*C12
A13: Head office staff | D13: =-'3 HR'!$D$27
A14: Head office running | D14: =-'5 Running'!$E$20
A15: Head office depreciation | D15: =-'4 Depreciation'!$G$8
A16: Head office development charge | D16: =-'6 Start-up'!$B$22
A17: Head office investment return | D17: =-'7 Returns'!$B$10
A18: Head office tax | D18: =-'8 Tax'!$B$6
A19: Head office target profit | D19: =-('9 Unit costs'!$B$15-'9 Unit costs'!$B$13)
A20: Venture surplus per month | D20: =SUM(D5:D19)
A21: Venture surplus per year | D21: =D20*12
A22: Units × unit surplus (must equal venture surplus) | D22: ='2 Customers'!$B$6*'11 Unit P&L'!$B$17

Sheet 13 Sales
A1: Sales assumptions — year one, the operating units open in year one
A2: The Start Up Loans template sheet. Volumes = units open × steady-state transactions × the month's share of steady state.
A4: Operating units open in year one | B4: ='1 Master'!$B$48
A5: Share of steady-state volume, by month | B5: 0.8125 | C5: 0.825 | D5: 0.8375 | E5: 0.85 | F5: 0.8625 | G5: 0.875 | H5: 0.8875 | I5: 0.9 | J5: 0.9125 | K5: 0.925 | L5: 0.9375 | M5: 0.95
A7: Product / month | B7: M1 | C7: M2 | D7: M3 | E7: M4 | F7: M5 | G7: M6 | H7: M7 | I7: M8 | J7: M9 | K7: M10 | L7: M11 | M7: M12 | N7: Year
A8: Drawn balance, per £1,000 carried for one month — volume | B8: =$B$4*'2 Customers'!$C$14*B$5 | C8: =$B$4*'2 Customers'!$C$14*C$5 | D8: =$B$4*'2 Customers'!$C$14*D$5 | E8: =$B$4*'2 Customers'!$C$14*E$5 | F8: =$B$4*'2 Customers'!$C$14*F$5 | G8: =$B$4*'2 Customers'!$C$14*G$5 | H8: =$B$4*'2 Customers'!$C$14*H$5 | I8: =$B$4*'2 Customers'!$C$14*I$5 | ... M8: =$B$4*'2 Customers'!$C$14*M$5 | N8: =SUM(B8:M8)
A9: Drawn balance, per £1,000 carried for one month — sales | B9: =B8*'2 Customers'!$D$14 | C9: =C8*'2 Customers'!$D$14 | D9: =D8*'2 Customers'!$D$14 | E9: =E8*'2 Customers'!$D$14 | F9: =F8*'2 Customers'!$D$14 | G9: =G8*'2 Customers'!$D$14 | H9: =H8*'2 Customers'!$D$14 | I9: =I8*'2 Customers'!$D$14 | ... M9: =M8*'2 Customers'!$D$14 | N9: =SUM(B9:M9)
A10: Drawn balance, per £1,000 carried for one month — cost of sales | B10: =B8*'2 Customers'!$F$14 | C10: =C8*'2 Customers'!$F$14 | D10: =D8*'2 Customers'!$F$14 | E10: =E8*'2 Customers'!$F$14 | F10: =F8*'2 Customers'!$F$14 | G10: =G8*'2 Customers'!$F$14 | H10: =H8*'2 Customers'!$F$14 | I10: =I8*'2 Customers'!$F$14 | ... M10: =M8*'2 Customers'!$F$14 | N10: =SUM(B10:M10)
A12: Total sales | B12: =B9 | C12: =C9 | D12: =D9 | E12: =E9 | F12: =F9 | G12: =G9 | H12: =H9 | I12: =I9 | ... N12: =N9
A13: Total cost of sales | B13: =B10 | C13: =C10 | D13: =D10 | E13: =E10 | F13: =F10 | G13: =G10 | H13: =H10 | I13: =I10 | ... N13: =N10
A14: Total volume | B14: =B8 | C14: =C8 | D14: =D8 | E14: =E8 | F14: =F8 | G14: =G8 | H14: =H8 | I14: =I8 | ... N14: =N8

Sheet 14 Cash flow
A1: Twelve-month cash-flow forecast — year one
A2: The Start Up Loans template sheet, with its stress test: revenue down by the rate on tab 1.
A4: Loan amount | B4: ='1 Master'!$B$51
A5: Loan interest rate (annual) | B5: ='1 Master'!$B$52
A6: Loan term (months) | B6: ='1 Master'!$B$53
A7: Monthly repayment = L × r ÷ (1 − (1 + r)^−n) | B7: =IF(B5=0,B4/B6,B4*(B5/12)/(1-(1+B5/12)^(-B6)))
A9: Line / month | B9: M1 | C9: M2 | D9: M3 | E9: M4 | F9: M5 | G9: M6 | H9: M7 | I9: M8 | J9: M9 | K9: M10 | L9: M11 | M9: M12 | N9: Year
A10: IN: sales | B10: ='13 Sales'!B12 | C10: ='13 Sales'!C12 | D10: ='13 Sales'!D12 | E10: ='13 Sales'!E12 | F10: ='13 Sales'!F12 | G10: ='13 Sales'!G12 | H10: ='13 Sales'!H12 | I10: ='13 Sales'!I12 | ... M10: ='13 Sales'!M12 | N10: =SUM(B10:M10)
A11: IN: loan | B11: ='1 Master'!$B$51 | C11: =0 | D11: =0 | E11: =0 | F11: =0 | G11: =0 | H11: =0 | I11: =0 | J11: =0 | ... M11: =0
A12: IN: other equity or grants | B12: ='1 Master'!$B$54 | C12: =0 | D12: =0 | E12: =0 | F12: =0 | G12: =0 | H12: =0 | I12: =0 | J12: =0 | ... M12: =0
A13: Total in | B13: =SUM(B10:B12) | C13: =SUM(C10:C12) | D13: =SUM(D10:D12) | E13: =SUM(E10:E12) | F13: =SUM(F10:F12) | G13: =SUM(G10:G12) | H13: =SUM(H10:H12) | I13: =SUM(I10:I12) | ... M13: =SUM(M10:M12) | N13: =SUM(B13:M13)
A14: OUT: cost of sales | B14: ='13 Sales'!B13 | C14: ='13 Sales'!C13 | D14: ='13 Sales'!D13 | E14: ='13 Sales'!E13 | F14: ='13 Sales'!F13 | G14: ='13 Sales'!G13 | H14: ='13 Sales'!H13 | I14: ='13 Sales'!I13 | ... M14: ='13 Sales'!M13
A15: OUT: staff (operating units, full from month one) | B15: ='1 Master'!$B$48*'3 HR'!$F$20 | C15: ='1 Master'!$B$48*'3 HR'!$F$20 | D15: ='1 Master'!$B$48*'3 HR'!$F$20 | E15: ='1 Master'!$B$48*'3 HR'!$F$20 | F15: ='1 Master'!$B$48*'3 HR'!$F$20 | G15: ='1 Master'!$B$48*'3 HR'!$F$20 | H15: ='1 Master'!$B$48*'3 HR'!$F$20 | I15: ='1 Master'!$B$48*'3 HR'!$F$20 | ... M15: ='1 Master'!$B$48*'3 HR'!$F$20
A16: OUT: staff (head office, year-one share) | B16: ='1 Master'!$B$49*'3 HR'!$D$27 | C16: ='1 Master'!$B$49*'3 HR'!$D$27 | D16: ='1 Master'!$B$49*'3 HR'!$D$27 | E16: ='1 Master'!$B$49*'3 HR'!$D$27 | F16: ='1 Master'!$B$49*'3 HR'!$D$27 | G16: ='1 Master'!$B$49*'3 HR'!$D$27 | H16: ='1 Master'!$B$49*'3 HR'!$D$27 | I16: ='1 Master'!$B$49*'3 HR'!$D$27 | ... M16: ='1 Master'!$B$49*'3 HR'!$D$27
A17: OUT: running costs, fixed (units) | B17: ='1 Master'!$B$48*'5 Running'!$E$11 | C17: ='1 Master'!$B$48*'5 Running'!$E$11 | D17: ='1 Master'!$B$48*'5 Running'!$E$11 | E17: ='1 Master'!$B$48*'5 Running'!$E$11 | F17: ='1 Master'!$B$48*'5 Running'!$E$11 | G17: ='1 Master'!$B$48*'5 Running'!$E$11 | H17: ='1 Master'!$B$48*'5 Running'!$E$11 | I17: ='1 Master'!$B$48*'5 Running'!$E$11 | ... M17: ='1 Master'!$B$48*'5 Running'!$E$11
A18: OUT: running costs, varying with volume (units) | B18: ='1 Master'!$B$48*'5 Running'!$E$12*'13 Sales'!B$5 | C18: ='1 Master'!$B$48*'5 Running'!$E$12*'13 Sales'!C$5 | D18: ='1 Master'!$B$48*'5 Running'!$E$12*'13 Sales'!D$5 | E18: ='1 Master'!$B$48*'5 Running'!$E$12*'13 Sales'!E$5 | F18: ='1 Master'!$B$48*'5 Running'!$E$12*'13 Sales'!F$5 | G18: ='1 Master'!$B$48*'5 Running'!$E$12*'13 Sales'!G$5 | H18: ='1 Master'!$B$48*'5 Running'!$E$12*'13 Sales'!H$5 | I18: ='1 Master'!$B$48*'5 Running'!$E$12*'13 Sales'!I$5 | ... M18: ='1 Master'!$B$48*'5 Running'!$E$12*'13 Sales'!M$5
A19: OUT: running costs (head office, year-one share) | B19: ='1 Master'!$B$49*'5 Running'!$E$20 | C19: ='1 Master'!$B$49*'5 Running'!$E$20 | D19: ='1 Master'!$B$49*'5 Running'!$E$20 | E19: ='1 Master'!$B$49*'5 Running'!$E$20 | F19: ='1 Master'!$B$49*'5 Running'!$E$20 | G19: ='1 Master'!$B$49*'5 Running'!$E$20 | H19: ='1 Master'!$B$49*'5 Running'!$E$20 | I19: ='1 Master'!$B$49*'5 Running'!$E$20 | ... M19: ='1 Master'!$B$49*'5 Running'!$E$20
A20: OUT: start-up costs and capital assets (units) | B20: ='1 Master'!$B$48*('6 Start-up'!$B$5+'4 Depreciation'!$F$5) | C20: =0 | D20: =0 | E20: =0 | F20: =0 | G20: =0 | H20: =0 | I20: =0 | J20: =0 | ... M20: =0
A21: OUT: development and capital assets (head office) | B21: ='6 Start-up'!$B$21+'4 Depreciation'!$F$8 | C21: =0 | D21: =0 | E21: =0 | F21: =0 | G21: =0 | H21: =0 | I21: =0 | J21: =0 | ... M21: =0
A22: OUT: loan repayment | B22: =$B$7 | C22: =$B$7 | D22: =$B$7 | E22: =$B$7 | F22: =$B$7 | G22: =$B$7 | H22: =$B$7 | I22: =$B$7 | ... M22: =$B$7
A23: Total out | B23: =SUM(B14:B22) | C23: =SUM(C14:C22) | D23: =SUM(D14:D22) | E23: =SUM(E14:E22) | F23: =SUM(F14:F22) | G23: =SUM(G14:G22) | H23: =SUM(H14:H22) | I23: =SUM(I14:I22) | ... M23: =SUM(M14:M22) | N23: =SUM(B23:M23)
A24: Net cash flow | B24: =B13-B23 | C24: =C13-C23 | D24: =D13-D23 | E24: =E13-E23 | F24: =F13-F23 | G24: =G13-G23 | H24: =H13-H23 | I24: =I13-I23 | ... M24: =M13-M23 | N24: =SUM(B24:M24)
A25: Opening balance | B25: ='1 Master'!$B$50 | C25: =B26 | D25: =C26 | E25: =D26 | F25: =E26 | G25: =F26 | H25: =G26 | I25: =H26 | J25: =I26 | ... M25: =L26
A26: Closing balance | B26: =B25+B24 | C26: =C25+C24 | D26: =D25+D24 | E26: =E25+E24 | F26: =F25+F24 | G26: =G25+G24 | H26: =H25+H24 | I26: =I25+I24 | ... M26: =M25+M24
A27: Stress: closing balance with revenue reduced | B27: ='1 Master'!$B$50+B24-B10*'1 Master'!$B$55 | C27: =B27+C24-C10*'1 Master'!$B$55 | D27: =C27+D24-D10*'1 Master'!$B$55 | E27: =D27+E24-E10*'1 Master'!$B$55 | F27: =E27+F24-F10*'1 Master'!$B$55 | G27: =F27+G24-G10*'1 Master'!$B$55 | H27: =G27+H24-H10*'1 Master'!$B$55 | I27: =H27+I24-I10*'1 Master'!$B$55 | J27: =I27+J24-J10*'1 Master'!$B$55 | ... M27: =L27+M24-M10*'1 Master'!$B$55
A29: Lowest closing balance in the year | B29: =MIN(B26:M26)
A30: Lowest closing balance under stress | B30: =MIN(B27:M27)
A31: Closing balance, month twelve | B31: =M26
A32: Cash needed = −(lowest closing balance) if negative, else zero | B32: =MAX(0,-B29)
A33: Cash needed under stress | B33: =MAX(0,-B30)

Sheet 15 Roll-out
A1: Roll-out — operating units by year, the loan schedule and capital spend
A2: Drives tabs 16 to 18. A cohort of units opens at the start of its year and follows the year-one volume profile on tab 13; units already open run at steady state. Blue cells are inputs.
A4: Year | B4: 1 | C4: 2 | D4: 3 | E4: 4 | F4: 5
A5: Operating units open at the year end | B5: 0.76 | C5: 3 | D5: 3 | E5: 3 | F5: 3
A6: New units opened in the year | B6: =B5 | C6: =C5-B5 | D6: =D5-C5 | E6: =E5-D5 | F6: =F5-E5
A7: Unit-months at steady-state volume = 12 × units open last year + new units × sum of the ramp | B7: =B6*SUM('13 Sales'!$B$5:$M$5) | C7: =12*B5+C6*SUM('13 Sales'!$B$5:$M$5) | D7: =12*C5+D6*SUM('13 Sales'!$B$5:$M$5) | E7: =12*D5+E6*SUM('13 Sales'!$B$5:$M$5) | F7: =12*E5+F6*SUM('13 Sales'!$B$5:$M$5)
A8: Head-office share staffed and run | B8: 1 | C8: 1 | D8: 1 | E8: 1 | F8: 1
A9: Equity raised in the year | B9: 5000000 | C9: 0 | D9: 0 | E9: 0 | F9: 0
A10: Operating units running at the year end = open last year + new units × the month-twelve share | B10: =B6*'13 Sales'!$M$5 | C10: =B5+C6*'13 Sales'!$M$5 | D10: =C5+D6*'13 Sales'!$M$5 | E10: =D5+E6*'13 Sales'!$M$5 | F10: =E5+F6*'13 Sales'!$M$5
A11: Loans to customers at the year end = balance lent per transaction × transactions per unit × units running | B11: ='1 Master'!$B$46*'2 Customers'!$B$10*B10 | C11: ='1 Master'!$B$46*'2 Customers'!$B$10*C10 | D11: ='1 Master'!$B$46*'2 Customers'!$B$10*D10 | E11: ='1 Master'!$B$46*'2 Customers'!$B$10*E10 | F11: ='1 Master'!$B$46*'2 Customers'!$B$10*F10
A12: Increase in loans to customers in the year | B12: =B11 | C12: =C11-B11 | D12: =D11-C11 | E12: =E11-D11 | F12: =F11-E11
A13: Deposits funding the book = book × (1 − capital share) | B13: =B11*(1-'1 Master'!$B$47) | C13: =C11*(1-'1 Master'!$B$47) | D13: =D11*(1-'1 Master'!$B$47) | E13: =E11*(1-'1 Master'!$B$47) | F13: =F11*(1-'1 Master'!$B$47)
A14: Capital held against the book = book × capital share | B14: =B11*'1 Master'!$B$47 | C14: =C11*'1 Master'!$B$47 | D14: =D11*'1 Master'!$B$47 | E14: =E11*'1 Master'!$B$47 | F14: =F11*'1 Master'!$B$47
A16: Loan drawn | B16: ='1 Master'!$B$51 | C16: =0 | D16: =0 | E16: =0 | F16: =0
A17: Loan balance at the start of the year | B17: ='1 Master'!$B$51 | C17: =B18 | D17: =C18 | E17: =D18 | F17: =E18
A18: Loan balance at the end of the year | B18: =IF((12*B$4)>='1 Master'!$B$53,0,IF('1 Master'!$B$52=0,MAX(0,'1 Master'!$B$51-'14 Cash flow'!$B$7*(12*B$4)),MAX(0,'1 Master'!$B$51*(1+'1 Master'!$B$52/12)^(12*B$4)-'14 Cash flow'!$B$7*((1+'1 Master'!$B$52/12)^(12*B$4)-1)/('1 Master'!$B$52/12)))) | C18: =IF((12*C$4)>='1 Master'!$B$53,0,IF('1 Master'!$B$52=0,MAX(0,'1 Master'!$B$51-'14 Cash flow'!$B$7*(12*C$4)),MAX(0,'1 Master'!$B$51*(1+'1 Master'!$B$52/12)^(12*C$4)-'14 Cash flow'!$B$7*((1+'1 Master'!$B$52/12)^(12*C$4)-1)/('1 Master'!$B$52/12)))) | D18: =IF((12*D$4)>='1 Master'!$B$53,0,IF('1 Master'!$B$52=0,MAX(0,'1 Master'!$B$51-'14 Cash flow'!$B$7*(12*D$4)),MAX(0,'1 Master'!$B$51*(1+'1 Master'!$B$52/12)^(12*D$4)-'14 Cash flow'!$B$7*((1+'1 Master'!$B$52/12)^(12*D$4)-1)/('1 Master'!$B$52/12)))) | E18: =IF((12*E$4)>='1 Master'!$B$53,0,IF('1 Master'!$B$52=0,MAX(0,'1 Master'!$B$51-'14 Cash flow'!$B$7*(12*E$4)),MAX(0,'1 Master'!$B$51*(1+'1 Master'!$B$52/12)^(12*E$4)-'14 Cash flow'!$B$7*((1+'1 Master'!$B$52/12)^(12*E$4)-1)/('1 Master'!$B$52/12)))) | F18: =IF((12*F$4)>='1 Master'!$B$53,0,IF('1 Master'!$B$52=0,MAX(0,'1 Master'!$B$51-'14 Cash flow'!$B$7*(12*F$4)),MAX(0,'1 Master'!$B$51*(1+'1 Master'!$B$52/12)^(12*F$4)-'14 Cash flow'!$B$7*((1+'1 Master'!$B$52/12)^(12*F$4)-1)/('1 Master'!$B$52/12))))
A19: Loan payments in the year | B19: ='14 Cash flow'!$B$7*MIN(12,MAX(0,'1 Master'!$B$53-12*(B$4-1))) | C19: ='14 Cash flow'!$B$7*MIN(12,MAX(0,'1 Master'!$B$53-12*(C$4-1))) | D19: ='14 Cash flow'!$B$7*MIN(12,MAX(0,'1 Master'!$B$53-12*(D$4-1))) | E19: ='14 Cash flow'!$B$7*MIN(12,MAX(0,'1 Master'!$B$53-12*(E$4-1))) | F19: ='14 Cash flow'!$B$7*MIN(12,MAX(0,'1 Master'!$B$53-12*(F$4-1)))
A20: Loan principal repaid = start balance − end balance | B20: =B17-B18 | C20: =C17-C18 | D20: =D17-D18 | E20: =E17-E18 | F20: =F17-F18
A21: Loan interest = payments − principal | B21: =B19-B20 | C21: =C19-C20 | D21: =D19-D20 | E21: =E19-E20 | F21: =F19-F20
A23: Capital spend on new units and, in year one, head office | B23: ='4 Depreciation'!$F$5*B6+'4 Depreciation'!$F$8 | C23: ='4 Depreciation'!$F$5*C6 | D23: ='4 Depreciation'!$F$5*D6 | E23: ='4 Depreciation'!$F$5*E6 | F23: ='4 Depreciation'!$F$5*F6
A24: Replacement of unit assets at the end of their life | B24: =SUMPRODUCT($B$31:$B$35,C31:C35) | C24: =SUMPRODUCT($B$31:$B$35,D31:D35) | D24: =SUMPRODUCT($B$31:$B$35,E31:E35) | E24: =SUMPRODUCT($B$31:$B$35,F31:F35) | F24: =SUMPRODUCT($B$31:$B$35,G31:G35)
A25: Replacement of head-office assets at the end of their life | B25: =IF(B$4>1,0,0) | C25: =IF(C$4>1,0,0) | D25: =IF(D$4>1,0,0) | E25: =IF(E$4>1,0,0) | F25: =IF(F$4>1,0,0)
A26: Fixed assets, net book value at the start of the year | B26: =0 | C26: =B28 | D26: =C28 | E26: =D28 | F26: =E28
A27: Depreciation charge = 12 × (per-unit depreciation × units + head-office depreciation), capped at what is left to write off | B27: =MIN(12*('4 Depreciation'!$G$5*B5+'4 Depreciation'!$G$8),B26+B23+B24+B25) | C27: =MIN(12*('4 Depreciation'!$G$5*C5+'4 Depreciation'!$G$8),C26+C23+C24+C25) | D27: =MIN(12*('4 Depreciation'!$G$5*D5+'4 Depreciation'!$G$8),D26+D23+D24+D25) | E27: =MIN(12*('4 Depreciation'!$G$5*E5+'4 Depreciation'!$G$8),E26+E23+E24+E25) | F27: =MIN(12*('4 Depreciation'!$G$5*F5+'4 Depreciation'!$G$8),F26+F23+F24+F25)
A28: Fixed assets, net book value at the end of the year | B28: =B26+B23+B24+B25-B27 | C28: =C26+C23+C24+C25-C27 | D28: =D26+D23+D24+D25-D27 | E28: =E26+E23+E24+E25-E27 | F28: =F26+F23+F24+F25-F27
A29: Replacement cost per unit of each cohort, by year — an asset bought in month one of the cohort's first year is replaced in the year that holds the month after its life ends
A30: Cohort (year the units opened) | B30: Units in the cohort | C30: Year 1 | D30: Year 2 | E30: Year 3 | F30: Year 4 | G30: Year 5
A31: 1 | B31: =B$6 | C31: =IF(B$4>$A31,0,0) | D31: =IF(C$4>$A31,0,0) | E31: =IF(D$4>$A31,0,0) | F31: =IF(E$4>$A31,0,0) | G31: =IF(F$4>$A31,0,0)
A32: 2 | B32: =C$6 | C32: =IF(B$4>$A32,0,0) | D32: =IF(C$4>$A32,0,0) | E32: =IF(D$4>$A32,0,0) | F32: =IF(E$4>$A32,0,0) | G32: =IF(F$4>$A32,0,0)
A33: 3 | B33: =D$6 | C33: =IF(B$4>$A33,0,0) | D33: =IF(C$4>$A33,0,0) | E33: =IF(D$4>$A33,0,0) | F33: =IF(E$4>$A33,0,0) | G33: =IF(F$4>$A33,0,0)
A34: 4 | B34: =E$6 | C34: =IF(B$4>$A34,0,0) | D34: =IF(C$4>$A34,0,0) | E34: =IF(D$4>$A34,0,0) | F34: =IF(E$4>$A34,0,0) | G34: =IF(F$4>$A34,0,0)
A35: 5 | B35: =F$6 | C35: =IF(B$4>$A35,0,0) | D35: =IF(C$4>$A35,0,0) | E35: =IF(D$4>$A35,0,0) | F35: =IF(E$4>$A35,0,0) | G35: =IF(F$4>$A35,0,0)

Sheet 16 Forecast P&L
A1: Forecast profit and loss — years one to 5
A2: Conventional accounting: start-up costs and head-office development are charged when paid; tax is charged on profit after losses brought forward. Costs are negative.
A4: Line | B4: Year 1 | C4: Year 2 | D4: Year 3 | E4: Year 4 | F4: Year 5 | G4: Total
A5: Revenue | B5: ='2 Customers'!$E$15*'15 Roll-out'!B7 | C5: ='2 Customers'!$E$15*'15 Roll-out'!C7 | D5: ='2 Customers'!$E$15*'15 Roll-out'!D7 | E5: ='2 Customers'!$E$15*'15 Roll-out'!E7 | F5: ='2 Customers'!$E$15*'15 Roll-out'!F7 | G5: =SUM(B5:F5)
A6: Cost of sales | B6: =-'2 Customers'!$G$15*'15 Roll-out'!B7 | C6: =-'2 Customers'!$G$15*'15 Roll-out'!C7 | D6: =-'2 Customers'!$G$15*'15 Roll-out'!D7 | E6: =-'2 Customers'!$G$15*'15 Roll-out'!E7 | F6: =-'2 Customers'!$G$15*'15 Roll-out'!F7 | G6: =SUM(B6:F6)
A7: Gross profit | B7: =B5+B6 | C7: =C5+C6 | D7: =D5+D6 | E7: =E5+E6 | F7: =F5+F6 | G7: =SUM(B7:F7)
A8: Staff — operating units | B8: =-'3 HR'!$F$20*12*'15 Roll-out'!B5 | C8: =-'3 HR'!$F$20*12*'15 Roll-out'!C5 | D8: =-'3 HR'!$F$20*12*'15 Roll-out'!D5 | E8: =-'3 HR'!$F$20*12*'15 Roll-out'!E5 | F8: =-'3 HR'!$F$20*12*'15 Roll-out'!F5 | G8: =SUM(B8:F8)
A9: Staff — head office | B9: =-'3 HR'!$D$27*12*'15 Roll-out'!B8 | C9: =-'3 HR'!$D$27*12*'15 Roll-out'!C8 | D9: =-'3 HR'!$D$27*12*'15 Roll-out'!D8 | E9: =-'3 HR'!$D$27*12*'15 Roll-out'!E8 | F9: =-'3 HR'!$D$27*12*'15 Roll-out'!F8 | G9: =SUM(B9:F9)
A10: Running costs — operating units | B10: =-('5 Running'!$E$11*12*'15 Roll-out'!B5+'5 Running'!$E$12*'15 Roll-out'!B7) | C10: =-('5 Running'!$E$11*12*'15 Roll-out'!C5+'5 Running'!$E$12*'15 Roll-out'!C7) | D10: =-('5 Running'!$E$11*12*'15 Roll-out'!D5+'5 Running'!$E$12*'15 Roll-out'!D7) | E10: =-('5 Running'!$E$11*12*'15 Roll-out'!E5+'5 Running'!$E$12*'15 Roll-out'!E7) | F10: =-('5 Running'!$E$11*12*'15 Roll-out'!F5+'5 Running'!$E$12*'15 Roll-out'!F7) | G10: =SUM(B10:F10)
A11: Running costs — head office | B11: =-'5 Running'!$E$20*12*'15 Roll-out'!B8 | C11: =-'5 Running'!$E$20*12*'15 Roll-out'!C8 | D11: =-'5 Running'!$E$20*12*'15 Roll-out'!D8 | E11: =-'5 Running'!$E$20*12*'15 Roll-out'!E8 | F11: =-'5 Running'!$E$20*12*'15 Roll-out'!F8 | G11: =SUM(B11:F11)
A12: Start-up costs of new units | B12: =-'6 Start-up'!$B$5*'15 Roll-out'!B6 | C12: =-'6 Start-up'!$B$5*'15 Roll-out'!C6 | D12: =-'6 Start-up'!$B$5*'15 Roll-out'!D6 | E12: =-'6 Start-up'!$B$5*'15 Roll-out'!E6 | F12: =-'6 Start-up'!$B$5*'15 Roll-out'!F6 | G12: =SUM(B12:F12)
A13: Head-office development | B13: =-'6 Start-up'!$B$21 | C13: =0 | D13: =0 | E13: =0 | F13: =0 | G13: =SUM(B13:F13)
A14: Depreciation | B14: =-'15 Roll-out'!B27 | C14: =-'15 Roll-out'!C27 | D14: =-'15 Roll-out'!D27 | E14: =-'15 Roll-out'!E27 | F14: =-'15 Roll-out'!F27 | G14: =SUM(B14:F14)
A15: Operating profit | B15: =B7+SUM(B8:B14) | C15: =C7+SUM(C8:C14) | D15: =D7+SUM(D8:D14) | E15: =E7+SUM(E8:E14) | F15: =F7+SUM(F8:F14) | G15: =SUM(B15:F15)
A16: Loan interest | B16: =-'15 Roll-out'!B21 | C16: =-'15 Roll-out'!C21 | D16: =-'15 Roll-out'!D21 | E16: =-'15 Roll-out'!E21 | F16: =-'15 Roll-out'!F21 | G16: =SUM(B16:F16)
A17: Profit before tax | B17: =B15+B16 | C17: =C15+C16 | D17: =D15+D16 | E17: =E15+E16 | F17: =F15+F16 | G17: =SUM(B17:F17)
A18: Losses brought forward | B18: =0 | C18: =B21 | D18: =C21 | E18: =D21 | F18: =E21
A19: Taxable profit = profit before tax less losses brought forward, not below zero | B19: =MAX(0,B17-B18) | C19: =MAX(0,C17-C18) | D19: =MAX(0,D17-D18) | E19: =MAX(0,E17-E18) | F19: =MAX(0,F17-F18)
A20: Tax | B20: =-B19*'1 Master'!$B$43 | C20: =-C19*'1 Master'!$B$43 | D20: =-D19*'1 Master'!$B$43 | E20: =-E19*'1 Master'!$B$43 | F20: =-F19*'1 Master'!$B$43 | G20: =SUM(B20:F20)
A21: Losses carried forward | B21: =MAX(0,B18-MAX(0,B17))+MAX(0,-B17) | C21: =MAX(0,C18-MAX(0,C17))+MAX(0,-C17) | D21: =MAX(0,D18-MAX(0,D17))+MAX(0,-D17) | E21: =MAX(0,E18-MAX(0,E17))+MAX(0,-E17) | F21: =MAX(0,F18-MAX(0,F17))+MAX(0,-F17)
A22: Profit after tax | B22: =B17+B20 | C22: =C17+C20 | D22: =D17+D20 | E22: =E17+E20 | F22: =F17+F20 | G22: =SUM(B22:F22)

Sheet 17 Forecast cash flow
A1: Forecast cash flow — years one to 5
A2: Tax is paid the year after it is charged. Year one closes at the same balance as tab 14. Outflows are negative.
A4: Line | B4: Year 1 | C4: Year 2 | D4: Year 3 | E4: Year 4 | F4: Year 5 | G4: Total
A5: Operating profit | B5: ='16 Forecast P&L'!B15 | C5: ='16 Forecast P&L'!C15 | D5: ='16 Forecast P&L'!D15 | E5: ='16 Forecast P&L'!E15 | F5: ='16 Forecast P&L'!F15 | G5: =SUM(B5:F5)
A6: Add back depreciation | B6: =-'16 Forecast P&L'!B14 | C6: =-'16 Forecast P&L'!C14 | D6: =-'16 Forecast P&L'!D14 | E6: =-'16 Forecast P&L'!E14 | F6: =-'16 Forecast P&L'!F14 | G6: =SUM(B6:F6)
A7: Loan interest paid | B7: ='16 Forecast P&L'!B16 | C7: ='16 Forecast P&L'!C16 | D7: ='16 Forecast P&L'!D16 | E7: ='16 Forecast P&L'!E16 | F7: ='16 Forecast P&L'!F16 | G7: =SUM(B7:F7)
A8: Tax paid (the previous year's charge) | B8: =0 | C8: ='16 Forecast P&L'!B20 | D8: ='16 Forecast P&L'!C20 | E8: ='16 Forecast P&L'!D20 | F8: ='16 Forecast P&L'!E20 | G8: =SUM(B8:F8)
A9: Cash from operations | B9: =SUM(B5:B8) | C9: =SUM(C5:C8) | D9: =SUM(D5:D8) | E9: =SUM(E5:E8) | F9: =SUM(F5:F8) | G9: =SUM(B9:F9)
A10: Capital spend on new units and head office | B10: =-'15 Roll-out'!B23 | C10: =-'15 Roll-out'!C23 | D10: =-'15 Roll-out'!D23 | E10: =-'15 Roll-out'!E23 | F10: =-'15 Roll-out'!F23 | G10: =SUM(B10:F10)
A11: Replacement of assets | B11: =-('15 Roll-out'!B24+'15 Roll-out'!B25) | C11: =-('15 Roll-out'!C24+'15 Roll-out'!C25) | D11: =-('15 Roll-out'!D24+'15 Roll-out'!D25) | E11: =-('15 Roll-out'!E24+'15 Roll-out'!E25) | F11: =-('15 Roll-out'!F24+'15 Roll-out'!F25) | G11: =SUM(B11:F11)
A12: Increase in loans to customers | B12: =-'15 Roll-out'!B12 | C12: =-'15 Roll-out'!C12 | D12: =-'15 Roll-out'!D12 | E12: =-'15 Roll-out'!E12 | F12: =-'15 Roll-out'!F12 | G12: =SUM(B12:F12)
A13: Cash used in investing | B13: =SUM(B10:B12) | C13: =SUM(C10:C12) | D13: =SUM(D10:D12) | E13: =SUM(E10:E12) | F13: =SUM(F10:F12) | G13: =SUM(B13:F13)
A14: Loan drawn | B14: ='15 Roll-out'!B16 | C14: ='15 Roll-out'!C16 | D14: ='15 Roll-out'!D16 | E14: ='15 Roll-out'!E16 | F14: ='15 Roll-out'!F16 | G14: =SUM(B14:F14)
A15: Loan principal repaid | B15: =-'15 Roll-out'!B20 | C15: =-'15 Roll-out'!C20 | D15: =-'15 Roll-out'!D20 | E15: =-'15 Roll-out'!E20 | F15: =-'15 Roll-out'!F20 | G15: =SUM(B15:F15)
A16: Equity raised | B16: ='15 Roll-out'!B9 | C16: ='15 Roll-out'!C9 | D16: ='15 Roll-out'!D9 | E16: ='15 Roll-out'!E9 | F16: ='15 Roll-out'!F9 | G16: =SUM(B16:F16)
A17: Deposits taken to fund the book | B17: ='15 Roll-out'!B12*(1-'1 Master'!$B$47) | C17: ='15 Roll-out'!C12*(1-'1 Master'!$B$47) | D17: ='15 Roll-out'!D12*(1-'1 Master'!$B$47) | E17: ='15 Roll-out'!E12*(1-'1 Master'!$B$47) | F17: ='15 Roll-out'!F12*(1-'1 Master'!$B$47) | G17: =SUM(B17:F17)
A18: Capital allocated to the book | B18: ='15 Roll-out'!B12*'1 Master'!$B$47 | C18: ='15 Roll-out'!C12*'1 Master'!$B$47 | D18: ='15 Roll-out'!D12*'1 Master'!$B$47 | E18: ='15 Roll-out'!E12*'1 Master'!$B$47 | F18: ='15 Roll-out'!F12*'1 Master'!$B$47 | G18: =SUM(B18:F18)
A19: Cash from financing | B19: =SUM(B14:B18) | C19: =SUM(C14:C18) | D19: =SUM(D14:D18) | E19: =SUM(E14:E18) | F19: =SUM(F14:F18) | G19: =SUM(B19:F19)
A20: Net cash flow | B20: =B9+B13+B19 | C20: =C9+C13+C19 | D20: =D9+D13+D19 | E20: =E9+E13+E19 | F20: =F9+F13+F19 | G20: =SUM(B20:F20)
A21: Opening cash | B21: ='1 Master'!$B$50 | C21: =B22 | D21: =C22 | E21: =D22 | F21: =E22
A22: Closing cash | B22: =B21+B20 | C22: =C21+C20 | D22: =D21+D20 | E22: =E21+E20 | F22: =F21+F20
A24: Lowest closing cash across the forecast | B24: =MIN(B22:F22)
A25: Extra funding needed over the forecast = −(lowest closing cash) if negative, else zero | B25: =MAX(0,-B24)

Sheet 18 Forecast balance sheet
A1: Forecast balance sheet — at the end of years one to 5
A2: No debtors, creditors or stock; the loan book is carried at its balance outstanding, funded by deposits and the capital held against it. Net assets must equal total equity in every year (last row reads zero).
A4: Line | B4: Year 1 | C4: Year 2 | D4: Year 3 | E4: Year 4 | F4: Year 5
A5: Fixed assets, net book value | B5: ='15 Roll-out'!B28 | C5: ='15 Roll-out'!C28 | D5: ='15 Roll-out'!D28 | E5: ='15 Roll-out'!E28 | F5: ='15 Roll-out'!F28
A6: Cash | B6: ='17 Forecast cash flow'!B22 | C6: ='17 Forecast cash flow'!C22 | D6: ='17 Forecast cash flow'!D22 | E6: ='17 Forecast cash flow'!E22 | F6: ='17 Forecast cash flow'!F22
A7: Loans to customers | B7: ='15 Roll-out'!B11 | C7: ='15 Roll-out'!C11 | D7: ='15 Roll-out'!D11 | E7: ='15 Roll-out'!E11 | F7: ='15 Roll-out'!F11
A8: Total assets | B8: =SUM(B5:B7) | C8: =SUM(C5:C7) | D8: =SUM(D5:D7) | E8: =SUM(E5:E7) | F8: =SUM(F5:F7)
A9: Loan outstanding | B9: ='15 Roll-out'!B18 | C9: ='15 Roll-out'!C18 | D9: ='15 Roll-out'!D18 | E9: ='15 Roll-out'!E18 | F9: ='15 Roll-out'!F18
A10: Tax payable | B10: =-'16 Forecast P&L'!B20 | C10: =-'16 Forecast P&L'!C20 | D10: =-'16 Forecast P&L'!D20 | E10: =-'16 Forecast P&L'!E20 | F10: =-'16 Forecast P&L'!F20
A11: Deposits funding the book | B11: ='15 Roll-out'!B13 | C11: ='15 Roll-out'!C13 | D11: ='15 Roll-out'!D13 | E11: ='15 Roll-out'!E13 | F11: ='15 Roll-out'!F13
A12: Total liabilities | B12: =SUM(B9:B11) | C12: =SUM(C9:C11) | D12: =SUM(D9:D11) | E12: =SUM(E9:E11) | F12: =SUM(F9:F11)
A13: Net assets | B13: =B8-B12 | C13: =C8-C12 | D13: =D8-D12 | E13: =E8-E12 | F13: =F8-F12
A15: Share capital — equity raised to date | B15: =SUM('15 Roll-out'!$B$9:B9) | C15: =SUM('15 Roll-out'!$B$9:C9) | D15: =SUM('15 Roll-out'!$B$9:D9) | E15: =SUM('15 Roll-out'!$B$9:E9) | F15: =SUM('15 Roll-out'!$B$9:F9)
A16: Retained profit — profit after tax to date | B16: =SUM('16 Forecast P&L'!$B$22:B22) | C16: =SUM('16 Forecast P&L'!$B$22:C22) | D16: =SUM('16 Forecast P&L'!$B$22:D22) | E16: =SUM('16 Forecast P&L'!$B$22:E22) | F16: =SUM('16 Forecast P&L'!$B$22:F22)
A17: Capital held against the book | B17: ='15 Roll-out'!B14 | C17: ='15 Roll-out'!C14 | D17: ='15 Roll-out'!D14 | E17: ='15 Roll-out'!E14 | F17: ='15 Roll-out'!F14
A18: Total equity | B18: =SUM(B15:B17) | C18: =SUM(C15:C17) | D18: =SUM(D15:D17) | E18: =SUM(E15:E17) | F18: =SUM(F15:F17)
A19: Net assets less total equity (must be zero) | B19: =B13-B18 | C19: =C13-C18 | D19: =D13-D18 | E19: =E13-E18 | F19: =F13-F18

Sheet 19 Check
A1: Check — the headline figures recomputed a second way, and the forecast reconciled
A2: Every row must read PASS. If one reads FAIL the workbook has been edited in a way that broke it.
A4: Check | B4: First value | C4: Second value | D4: Result
A5: Margin of safety on the pricing tab equals surplus ÷ whole cost on the unit P&L | B5: ='10 Pricing'!$B$6 | C5: ='11 Unit P&L'!$B$18 | D5: =IF(ABS(B5-C5)<0.00001,"PASS","FAIL")
A6: At the required price, surplus ÷ whole cost equals the target margin of safety | B6: ='1 Master'!$B$45 | C6: ='11 Unit P&L'!$C$18 | D6: =IF(ABS(B6-C6)<0.00001,"PASS","FAIL")
A7: Venture surplus equals units × unit surplus | B7: ='12 Venture P&L'!$D$20 | C7: ='12 Venture P&L'!$D$22 | D7: =IF(ABS(B7-C7)<0.00001,"PASS","FAIL")
A8: Cash chain: closing month twelve = opening month one + sum of net cash flows | B8: ='14 Cash flow'!M26 | C8: ='14 Cash flow'!B25+SUM('14 Cash flow'!B24:M24) | D8: =IF(ABS(B8-C8)<0.00001,"PASS","FAIL")
A9: Year-one volume equals units open × steady-state transactions × sum of the ramp | B9: ='13 Sales'!N14 | C9: ='1 Master'!$B$48*'2 Customers'!$B$10*SUM('13 Sales'!B5:M5) | D9: =IF(ABS(B9-C9)<0.00001,"PASS","FAIL")
A10: Whole cost per unit equals unit's own costs + head office allocation | B10: ='9 Unit costs'!$B$17 | C10: ='9 Unit costs'!$B$12+'9 Unit costs'!$B$16 | D10: =IF(ABS(B10-C10)<0.00001,"PASS","FAIL")
A11: Margin of safety on the pricing tab equals the builder's own computation (base scenario only) | B11: ='10 Pricing'!$B$6 | C11: ='10 Pricing'!$B$56 | D11: =IF('1 Master'!$B$4<>1,"n/a",IF(ABS(B11-C11)<0.00001,"PASS","FAIL"))
A12: Forecast year one opens the same number of units as the twelve-month forecast | B12: ='15 Roll-out'!B5 | C12: ='1 Master'!$B$48 | D12: =IF(ABS(B12-C12)<0.00001,"PASS","FAIL")
A13: Forecast year-one closing cash equals month twelve on the twelve-month forecast | B13: ='17 Forecast cash flow'!B22 | C13: ='14 Cash flow'!M26 | D13: =IF(ABS(B13-C13)<0.00001,"PASS","FAIL")
A14: Balance sheet balances in every forecast year — largest difference is zero | B14: =MAX('18 Forecast balance sheet'!B19:F19) | C14: =0 | D14: =IF(ABS(B14-C14)<0.00001,"PASS","FAIL")
A15: Balance sheet balances in every forecast year — smallest difference is zero | B15: =MIN('18 Forecast balance sheet'!B19:F19) | C15: =0 | D15: =IF(ABS(B15-C15)<0.00001,"PASS","FAIL")
A17: All checks | D17: =IF(COUNTIF(D5:D15,"FAIL")=0,"ALL CHECKS PASS","CHECK FAILED")
A18: Scenario in force on tab 1 (1 = base) | D18: ='1 Master'!$B$4
